xmovie/__init__.py
xmovie/_version.py
xmovie/core.py
xmovie/presets.py
xmovie/test/test_core.py
xmovie/test/test_presets.py
xmovie-0.3.1.dist-info/LICENSE
xmovie-0.3.1.dist-info/METADATA
xmovie-0.3.1.dist-info/WHEEL
xmovie-0.3.1.dist-info/top_level.txt
xmovie-0.3.1.dist-info/RECORD
